basex_ex/__init__.py
basex_ex/ada.py
basex_ex/bender.py
basex_ex/lygia.py
basex_ex/tables.py
basex_ex-1.1.1.dist-info/METADATA
basex_ex-1.1.1.dist-info/WHEEL
basex_ex-1.1.1.dist-info/top_level.txt
basex_ex-1.1.1.dist-info/RECORD
