Metadata-Version: 2.1
Name: basex-ex
Version: 1.1.1
Summary: Tools for EX Analysis
Author: pin-people
Author-email: rodrigo.toledo@pinpeople.com.br
Requires-Dist: numpy (~=1.24.3)
Requires-Dist: pandas (~=2.0.2)
Requires-Dist: scipy (~=1.10.1)
Requires-Dist: matplotlib (~=3.7.1)
Requires-Dist: matplotlib-venn (~=0.11.9)
